flask_file_router/__init__.py
flask_file_router/config.py
flask_file_router/router.py
flask_file_router/utils.py
flask_file_router-0.0.5.dist-info/LICENSE.txt
flask_file_router-0.0.5.dist-info/METADATA
flask_file_router-0.0.5.dist-info/WHEEL
flask_file_router-0.0.5.dist-info/top_level.txt
flask_file_router-0.0.5.dist-info/RECORD
