Metadata-Version: 2.1
Name: flask-file-router
Version: 0.0.5
Summary: File Based Routing for Flask Server
Home-page: https://github.com/kaush26/flask-file-router
Author: Kaushal Prasad Balmiki
Author-email: kaushalprasad2611@gmail.com
Project-URL: repository, https://github.com/kaush26/flask-file-router
Keywords: File Router,Flask,API,Python,Server
Classifier: Programming Language :: Python :: 3
Classifier: License :: OSI Approved :: MIT License
Classifier: Operating System :: OS Independent
Requires-Python: >=3.7
License-File: LICENSE.txt
Requires-Dist: Flask
